agent_connector/__init__.py
agent_connector/tools/__init__.py
agent_connector/tools/agent_connector_tool.py
agent_connector/tools/nexus_client.py
agent_connector/tools/utils.py
agent_connector/yamls/agent_connector_tool.yaml
tests/__init__.py
tests/test_agent_connector_tool.py
agent_connector-0.0.4.dist-info/LICENSE
agent_connector-0.0.4.dist-info/METADATA
agent_connector-0.0.4.dist-info/WHEEL
agent_connector-0.0.4.dist-info/entry_points.txt
agent_connector-0.0.4.dist-info/top_level.txt
agent_connector-0.0.4.dist-info/RECORD
