Metadata-Version: 2.1
Name: agent-connector
Version: 0.0.4
Summary: This is my tools package
Home-page: https://github.com/cxbxmxcx/Agent-Connector
Author: Micheal Lanham
Author-email: cxbxmxcx@gmail.com
License: UNKNOWN
Project-URL: Documentation, https://github.com/cxbxmxcx/Agent-Connector
Project-URL: Source, https://github.com/cxbxmxcx/Agent-Connector
Project-URL: Tracker, https://github.com/cxbxmxcx/Agent-Connector/issues
Platform: UNKNOWN
